.gitignore
LICENSE
MANIFEST.in
README.rst
screenshot.png
setup.py
redrum/__init__.py
redrum/__main__.py
redrum/redrum.ini
redrum/redrum.py
redrum/tune.py
redrum/tune_gui.py
redrum/version.py
redrum.egg-info/PKG-INFO
redrum.egg-info/SOURCES.txt
redrum.egg-info/dependency_links.txt
redrum.egg-info/entry_points.txt
redrum.egg-info/requires.txt
redrum.egg-info/top_level.txt
systemd/redrum.service
systemd/redrum.timer