Metadata-Version: 2.1
Name: redrum
Version: 1.5.3
Summary: uses math to select wallpapers from Reddit
Home-page: https://github.com/evidlo/redrum
Author: Evan Widloski
Author-email: evan@evanw.org
License: MIT
Keywords: Reddit wallpaper changer
Classifier: Programming Language :: Python :: 2
Classifier: Programming Language :: Python :: 3
License-File: LICENSE
Requires-Dist: requests
Requires-Dist: configparser
Provides-Extra: tune
Requires-Dist: matplotlib; extra == "tune"
Requires-Dist: numpy; extra == "tune"
